commands/__init__.py
commands/to.py
helpers/__init__.py
helpers/external_command.py
helpers/filer.py
helpers/itemsetter.py
subcommands/__init__.py
subcommands/do.py
subcommands/doing.py
subcommands/done.py
todonepy-4.0.9.dist-info/entry_points.txt
todonepy-4.0.9.dist-info/LICENSE
todonepy-4.0.9.dist-info/WHEEL
todonepy-4.0.9.dist-info/METADATA
todonepy-4.0.9.dist-info/RECORD
