Metadata-Version: 2.1
Name: todonepy
Version: 4.0.9
Summary: A developed command-line task manager
Home-page: https://pypi.org/project/ToDonePy/
License: GPL-3.0+
Author: rbpatt2019
Author-email: rb.patterson.cross@gmail.com
Requires-Python: >=3.7,<4.0
Classifier: Development Status :: 5 - Production/Stable
Classifier: Environment :: Console
Classifier: Intended Audience :: Developers
Classifier: Intended Audience :: End Users/Desktop
Classifier: Intended Audience :: Science/Research
Classifier: License :: OSI Approved :: GNU General Public License v3 (GPLv3)
Classifier: License :: OSI Approved :: GNU General Public License v3 or later (GPLv3+)
Classifier: Natural Language :: English
Classifier: Operating System :: MacOS :: MacOS X
Classifier: Operating System :: Unix
Classifier: Programming Language :: Python :: 3
Classifier: Programming Language :: Python :: 3.7
Classifier: Programming Language :: Python :: 3.8
Project-URL: Documentation, https://todonepy.readthedocs.io/en/latest/
Project-URL: Repository, https://github.com/rbpatt2019/ToDonePy
